MANIFEST.in
README.md
setup.py
NHentai/__init__.py
NHentai/asynch/__init__.py
NHentai/asynch/application/__init__.py
NHentai/asynch/application/use_cases/__init__.py
NHentai/asynch/application/use_cases/get_comments.py
NHentai/asynch/application/use_cases/get_doujin.py
NHentai/asynch/application/use_cases/get_page.py
NHentai/asynch/application/use_cases/get_popular_now.py
NHentai/asynch/application/use_cases/get_random.py
NHentai/asynch/application/use_cases/search_doujin.py
NHentai/asynch/infra/__init__.py
NHentai/asynch/infra/adapters/__init__.py
NHentai/asynch/infra/adapters/brokers/__init__.py
NHentai/asynch/infra/adapters/brokers/broker_interface.py
NHentai/asynch/infra/adapters/brokers/implementations/__init__.py
NHentai/asynch/infra/adapters/brokers/implementations/pubsub.py
NHentai/asynch/infra/adapters/repositories/__init__.py
NHentai/asynch/infra/adapters/repositories/hentai/__init__.py
NHentai/asynch/infra/adapters/repositories/hentai/hentai_interface.py
NHentai/asynch/infra/adapters/repositories/hentai/implementations/__init__.py
NHentai/asynch/infra/adapters/repositories/hentai/implementations/nhentai.py
NHentai/asynch/infra/adapters/request/__init__.py
NHentai/asynch/infra/adapters/request/http/__init__.py
NHentai/asynch/infra/adapters/request/http/implementations/__init__.py
NHentai/asynch/infra/adapters/request/http/implementations/asynk.py
NHentai/asynch/infra/adapters/request/http/interfaces/__init__.py
NHentai/asynch/infra/adapters/request/http/interfaces/request.py
NHentai/asynch/infra/adapters/request/http/interfaces/response.py
NHentai/asynch/infra/entrypoints/lib/__init__.py
NHentai/core/__init__.py
NHentai/core/cache.py
NHentai/core/handler.py
NHentai/core/logging.py
NHentai/core/propagate.py
NHentai/core/auth/__init__.py
NHentai/core/auth/google/__init__.py
NHentai/core/helpers/__init__.py
NHentai/core/helpers/cloudflare.py
NHentai/core/interfaces/__init__.py
NHentai/core/interfaces/base_dataclass.py
NHentai/core/interfaces/doujin.py
dev_nhentai_build.egg-info/PKG-INFO
dev_nhentai_build.egg-info/SOURCES.txt
dev_nhentai_build.egg-info/dependency_links.txt
dev_nhentai_build.egg-info/not-zip-safe
dev_nhentai_build.egg-info/requires.txt
dev_nhentai_build.egg-info/top_level.txt