Metadata-Version: 2.1
Name: dev-nhentai-build
Version: 0.0.13
Summary: NHentai Python API made using webscraping.
Home-page: https://github.com/AlexandreSenpai/NHentai-API
Author: AlexandreSenpai
Author-email: alexandrebsramos@hotmail.com
License: MIT
Keywords: Tagshentai,nhentai,nhentai.net,API,NSFW
Platform: UNKNOWN
Classifier: Programming Language :: Python :: 3
Classifier: License :: OSI Approved :: MIT License
Classifier: Operating System :: OS Independent
